{
	"$schema": "https://schema.management.azure.com/schemas/2015-01-01/deploymentParameters.json#",
	"contentVersion": "1.0.0.0",
	"parameters": {
		"workspaceName": {
			"value": "mithun-synapse1"
		},
		"mithun-synapse1-WorkspaceDefaultSqlServer_connectionString": {
			"value": "Integrated Security=False;Encrypt=True;Connection Timeout=30;Data Source=tcp:mithun-synapse1.sql.azuresynapse.net,1433;Initial Catalog=@{linkedService().DBName}"
		},
		"mithun-synapse1-WorkspaceDefaultStorage_properties_typeProperties_url": {
			"value": "https://mithunstorage97.dfs.core.windows.net"
		}
	}
}